autodc/__init__.py
autodc/data_augmentation.py
autodc/data_processing.py
autodc/edge_case_selection.py
autodc/outlier_detection.py
autodc/setup.py
autodc-1.0.6.dist-info/LICENSE
autodc-1.0.6.dist-info/METADATA
autodc-1.0.6.dist-info/WHEEL
autodc-1.0.6.dist-info/top_level.txt
autodc-1.0.6.dist-info/RECORD
