Metadata-Version: 2.1
Name: autodc
Version: 1.0.6
Summary: Auto DC
Home-page: https://github.com/akashanairhg/audtoDC
Author: akashanair92
Author-email: akashanair92@gmail.com
License: UNKNOWN
Platform: UNKNOWN
Classifier: Programming Language :: Python :: 3
Classifier: License :: OSI Approved :: MIT License
Classifier: Operating System :: OS Independent
License-File: LICENSE
